pastel_gateway_sdk/__init__.py
pastel_gateway_sdk/api_client.py
pastel_gateway_sdk/api_response.py
pastel_gateway_sdk/configuration.py
pastel_gateway_sdk/exceptions.py
pastel_gateway_sdk/gateway_api_client.py
pastel_gateway_sdk/py.typed
pastel_gateway_sdk/rest.py
pastel_gateway_sdk/api/__init__.py
pastel_gateway_sdk/api/account_api.py
pastel_gateway_sdk/api/admin_api.py
pastel_gateway_sdk/api/api_keys_api.py
pastel_gateway_sdk/api/cascade_api.py
pastel_gateway_sdk/api/collection_api.py
pastel_gateway_sdk/api/key_auth_api.py
pastel_gateway_sdk/api/login_api.py
pastel_gateway_sdk/api/nft_api.py
pastel_gateway_sdk/api/sense_api.py
pastel_gateway_sdk/api/users_api.py
pastel_gateway_sdk/models/__init__.py
pastel_gateway_sdk/models/api_key.py
pastel_gateway_sdk/models/api_key_create.py
pastel_gateway_sdk/models/body_login_reset_password.py
pastel_gateway_sdk/models/body_users_create_user_open.py
pastel_gateway_sdk/models/body_users_update_user_me.py
pastel_gateway_sdk/models/client_with_secret.py
pastel_gateway_sdk/models/collection_registration_result.py
pastel_gateway_sdk/models/collection_registration_result_status_messages_inner.py
pastel_gateway_sdk/models/http_validation_error.py
pastel_gateway_sdk/models/location_inner.py
pastel_gateway_sdk/models/msg.py
pastel_gateway_sdk/models/nft_properties_external.py
pastel_gateway_sdk/models/req_status.py
pastel_gateway_sdk/models/request_result.py
pastel_gateway_sdk/models/result_registration_result.py
pastel_gateway_sdk/models/status.py
pastel_gateway_sdk/models/token.py
pastel_gateway_sdk/models/user.py
pastel_gateway_sdk/models/user_create.py
pastel_gateway_sdk/models/user_create_with_key.py
pastel_gateway_sdk/models/user_id_or_email.py
pastel_gateway_sdk/models/user_update.py
pastel_gateway_sdk/models/user_with_key.py
pastel_gateway_sdk/models/validation_error.py
pastel_gateway_sdk-0.1.5.dist-info/METADATA
pastel_gateway_sdk-0.1.5.dist-info/WHEEL
pastel_gateway_sdk-0.1.5.dist-info/top_level.txt
pastel_gateway_sdk-0.1.5.dist-info/RECORD
